texplot/__init__.py
texplot/__main__.py
texplot/__version__.py
texplot/display_utilities.py
texplot/plot_utilities.py
texplot/examples/__init__.py
texplot/examples/plot_bifurcation_diagram.py
texplot/examples/plot_function.py
texplot/examples/plot_lorenz.py
texplot-0.0.11.dist-info/licenses/AUTHORS.txt
texplot-0.0.11.dist-info/licenses/LICENSE.txt
texplot-0.0.11.dist-info/METADATA
texplot-0.0.11.dist-info/WHEEL
texplot-0.0.11.dist-info/top_level.txt
texplot-0.0.11.dist-info/RECORD
