Metadata-Version: 2.4
Name: texplot
Version: 0.0.11
Summary: Enhance your matplotlib plots with publication-quality style
Home-page: https://github.com/ameli/texplot
Download-URL: https://github.com/ameli/texplot/archive/main.zip
Author: Siavash Ameli
Author-email: sameli@berkeley.edu
Project-URL: Documentation, https://github.com/ameli/texplot/blob/main/README.rst
Project-URL: Source, https://github.com/ameli/texplot
Project-URL: Tracker, https://github.com/ameli/texplot/issues
Keywords: matplotlib plotting latex
Platform: Linux
Platform: OSX
Platform: Windows
Classifier: Programming Language :: Python
Classifier: Programming Language :: Python :: 3.9
Classifier: Programming Language :: Python :: 3.10
Classifier: Programming Language :: Python :: 3.11
Classifier: Programming Language :: Python :: 3.12
Classifier: Programming Language :: Python :: Implementation :: CPython
Classifier: License :: OSI Approved :: BSD License
Classifier: Operating System :: POSIX :: Linux
Classifier: Operating System :: Microsoft :: Windows
Classifier: Operating System :: MacOS
Classifier: Natural Language :: English
Classifier: Intended Audience :: Science/Research
Classifier: Intended Audience :: Developers
Classifier: Topic :: Software Development
Classifier: Topic :: Software Development :: Libraries :: Python Modules
Classifier: Topic :: Scientific/Engineering
Requires-Python: >=3.9
License-File: LICENSE.txt
License-File: AUTHORS.txt
Requires-Dist: matplotlib
Provides-Extra: test
Provides-Extra: docs
Dynamic: author
Dynamic: author-email
Dynamic: classifier
Dynamic: description
Dynamic: description-content-type
Dynamic: download-url
Dynamic: home-page
Dynamic: keywords
Dynamic: license-file
Dynamic: platform
Dynamic: project-url
Dynamic: provides-extra
Dynamic: requires-dist
Dynamic: requires-python
Dynamic: summary
